vidtest/__init__.py
vidtest/pluto.py
testvid-0.0.1.dist-info/LICENSE.md
testvid-0.0.1.dist-info/METADATA
testvid-0.0.1.dist-info/WHEEL
testvid-0.0.1.dist-info/top_level.txt
testvid-0.0.1.dist-info/RECORD
