Metadata-Version: 2.1
Name: testvid
Version: 0.0.1
Summary: test test test
Home-page: UNKNOWN
Author: me
Author-email: <mail@example.com>
License: UNKNOWN
Platform: UNKNOWN
Classifier: Development Status :: 1 - Planning
Classifier: Intended Audience :: Developers
Classifier: Programming Language :: Python :: 3
Classifier: Operating System :: Microsoft :: Windows
License-File: LICENSE.md
Requires-Dist: numpy
Requires-Dist: matplotlib
